rhino3dm/__init__.py
rhino3dm/__init__.pyi
rhino3dm/_rhino3dm.cpython-312-darwin.so
rhino3dm/py.typed
rhino3dm-8.17.0.dist-info/LICENSE
rhino3dm-8.17.0.dist-info/METADATA
rhino3dm-8.17.0.dist-info/WHEEL
rhino3dm-8.17.0.dist-info/top_level.txt
rhino3dm-8.17.0.dist-info/RECORD
