Metadata-Version: 2.1
Name: rhino3dm
Version: 8.17.0
Summary: Python library based on OpenNURBS with a RhinoCommon style
Author: Robert McNeel & Associates
Author-email: steve@mcneel.com
License-File: LICENSE
